keboola/csvwriter/__init__.py
keboola/csvwriter/core.py
keboola.csvwriter-1.0.1.dist-info/LICENSE
keboola.csvwriter-1.0.1.dist-info/METADATA
keboola.csvwriter-1.0.1.dist-info/WHEEL
keboola.csvwriter-1.0.1.dist-info/top_level.txt
keboola.csvwriter-1.0.1.dist-info/RECORD
