Metadata-Version: 2.1
Name: keboola.csvwriter
Version: 1.0.1
Summary: ElasticDictWriter module based on Python csv package ensuring consistent header in the final CSV.
Home-page: https://bitbucket.org/kds_consulting_team/python-csv-writer/src/master/
Author: Keboola Component Factory Team
Author-email: support@keboola.com
License: UNKNOWN
Project-URL: Documentation, https://htmlpreview.github.io/?https://bitbucket.org/kds_consulting_team/python-csv-writer/raw/92caae145a6eb38f0615c98620803505aee4ec88/docs/api-html/keboola/csvwriter/core.html
Platform: UNKNOWN
Classifier: Programming Language :: Python :: 3
Classifier: License :: OSI Approved :: MIT License
Classifier: Operating System :: OS Independent
Classifier: Intended Audience :: Developers
Classifier: Intended Audience :: Information Technology
Classifier: Intended Audience :: Education
Classifier: Topic :: Software Development :: Libraries
Classifier: Topic :: Software Development :: Libraries :: Python Modules
Requires-Python: >=3.7
